README.md
setup.py
epl.protobuf.egg-info/PKG-INFO
epl.protobuf.egg-info/SOURCES.txt
epl.protobuf.egg-info/dependency_links.txt
epl.protobuf.egg-info/not-zip-safe
epl.protobuf.egg-info/requires.txt
epl.protobuf.egg-info/top_level.txt
epl/protobuf/__init__.py
epl/protobuf/geometry_pb2.py
epl/protobuf/geometry_service_pb2_grpc.py
epl/protobuf/query_pb2.py
epl/protobuf/stac_pb2.py
epl/protobuf/stac_service_pb2_grpc.py