Metadata-Version: 1.2
Name: epl.protobuf
Version: 0.4.8
Summary: generated protobufs for geometry and STAC
Home-page: https://github.com/geo-grpc/api
Author: David Raleigh
Author-email: davidraleigh@gmail.com
License: Apache 2.0
Platform: UNKNOWN
Classifier: Programming Language :: Python
Classifier: Programming Language :: Python :: 3
Classifier: Programming Language :: Python :: 3.5
Classifier: Programming Language :: Python :: 3.6
Requires-Python: >3.5.2
